README.md
setup.py
algorithm_analyse/__init__.py
algorithm_analyse/analyse.py
algorithm_analyse.egg-info/PKG-INFO
algorithm_analyse.egg-info/SOURCES.txt
algorithm_analyse.egg-info/dependency_links.txt
algorithm_analyse.egg-info/entry_points.txt
algorithm_analyse.egg-info/top_level.txt